{"chunk_definitions":[{"chunk_id":"cvp9w8edrcqqs","chunk_label":"unnamed-chunk-1","document_id":"358E3D30","expansion_state":0,"options":{"engine":"r","label":"unnamed-chunk-1"},"row":31,"row_count":1,"visible":true},{"chunk_id":"c9ugy18cjokks","chunk_label":"unnamed-chunk-3","document_id":"358E3D30","expansion_state":0,"options":{"engine":"r","label":"unnamed-chunk-9"},"row":260,"row_count":1,"visible":true},{"chunk_id":"cipkskfzd60t8","chunk_label":"unnamed-chunk-5","document_id":"358E3D30","expansion_state":0,"options":{"engine":"r","label":"unnamed-chunk-12"},"row":367,"row_count":1,"visible":true},{"chunk_id":"c9fc1lyb6hrix","chunk_label":"unnamed-chunk-6","document_id":"358E3D30","expansion_state":0,"options":{"engine":"r","label":"unnamed-chunk-11"},"row":393,"row_count":1,"visible":true}],"doc_write_time":1522955851}